walkerlayout/__init__.py
walkerlayout/walkerlayout.py
walkerlayout-1.0.2.dist-info/LICENSE
walkerlayout-1.0.2.dist-info/METADATA
walkerlayout-1.0.2.dist-info/WHEEL
walkerlayout-1.0.2.dist-info/top_level.txt
walkerlayout-1.0.2.dist-info/RECORD
