Metadata-Version: 2.1
Name: walkerlayout
Version: 1.0.2
Summary: A time-linear Python implementation of Walker's algorithm for level-based tree layouting/drawing
Author: Elias Foramitti
Author-email: elias@foramitti.com
License: MIT
Project-URL: GitHub, https://github.com/EliasLF/walkerlayout
License-File: LICENSE
